pytwee/__init__.py
pytwee/__main__.py
pytwee/story.py
pytwee/twee.py
pytwee/twee2.py
pytwee/twee3.py
pytwee-0.3.3.dist-info/licenses/LICENSE
pytwee-0.3.3.dist-info/METADATA
pytwee-0.3.3.dist-info/WHEEL
pytwee-0.3.3.dist-info/entry_points.txt
pytwee-0.3.3.dist-info/top_level.txt
pytwee-0.3.3.dist-info/RECORD
