Metadata-Version: 2.4
Name: pytwee
Version: 0.3.3
Summary: A parser for the twee format
Author-email: Xing Ji <me@xingji.me>
License-Expression: MIT
Project-URL: Homepage, https://pytwee.readthedocs.io
Project-URL: Repository, https://github.com/jixingcn/pytwee
Project-URL: Changelog, https://github.com/jixingcn/pytwee/blob/main/CHANGELOG.rst
Project-URL: Issues, https://github.com/jixingcn/pytwee/issues
Keywords: twine,twinery,twee,twee2,twee3,story
Classifier: Development Status :: 3 - Alpha
Classifier: Environment :: Web Environment
Classifier: Operating System :: OS Independent
Classifier: Programming Language :: Python :: 3
Classifier: Topic :: Documentation
Classifier: Topic :: Utilities
Requires-Python: >=3.7
License-File: LICENSE
Dynamic: license-file
